LICENSE
README.md
pyproject.toml
setup.cfg
src/ge_core.egg-info/PKG-INFO
src/ge_core.egg-info/SOURCES.txt
src/ge_core.egg-info/dependency_links.txt
src/ge_core.egg-info/requires.txt
src/ge_core.egg-info/top_level.txt
src/gecore/__init__.py
src/gecore/__main__.py
src/gecore/common/__init__.py
src/gecore/common/destination.py
src/gecore/common/i3d_attributes.py
src/gecore/common/source.py
src/gecore/converters/__init__.py
src/gecore/converters/i3d/__init__.py
src/gecore/converters/i3d/i3d_reader.py
src/gecore/converters/i3d/i3d_writer.py
src/gecore/xml_handlers/__init__.py
src/gecore/xml_handlers/elemtree_adapter.py
src/gecore/xml_handlers/lxml_adapter.py
src/gecore/xml_handlers/xml_interface.py