Metadata-Version: 2.1
Name: ge-core
Version: 0.1.0
Summary: A library for performing all sorts of operations involved in modding for Giants Engine games
Home-page: https://github.com/StjerneIdioten/GE-Core
Author: StjerneIdioten
Author-email: stjerneidioten@gmail.com
License: UNKNOWN
Project-URL: Bug Tracker, https://github.com/StjerneIdioten/GE-Core/issues
Platform: UNKNOWN
Classifier: Development Status :: 2 - Pre-Alpha
Classifier: Programming Language :: Python :: 3.8
Classifier: Programming Language :: Python :: 3.9
Classifier: License :: OSI Approved :: GNU General Public License v3 (GPLv3)
Classifier: Operating System :: OS Independent
Requires-Python: >=3.8
License-File: LICENSE
